CHANGELOG.txt
LICENSE.txt
MANIFEST.in
README.txt
setup.py
datatranslation/__init__.py
datatranslation.egg-info/PKG-INFO
datatranslation.egg-info/SOURCES.txt
datatranslation.egg-info/dependency_links.txt
datatranslation.egg-info/top_level.txt