Metadata-Version: 1.1
Name: datatranslation
Version: 0.0.1
Summary: This is dictionary translation library there are three input parameter where we have to cahnge values in the dictionary
Home-page: UNKNOWN
Author: sairam
Author-email: saira160305@gmail.com
License: UNKNOWN
Keywords: python
Platform: UNKNOWN
Classifier: Development Status :: 1 - Planning
Classifier: Intended Audience :: Developers
Classifier: Programming Language :: Python :: 3
Classifier: Operating System :: Unix
Classifier: Operating System :: MacOS :: MacOS X
Classifier: Operating System :: Microsoft :: Windows
